{
    "gini": 0.36216589503170843,
    "output": {
        "lines": 102812,
        "added": 47950,
        "refactor": 0.5336147531416566
    },
    "since": "2020-08-28T14:38:11.000000000",
    "until": "2021-02-27T21:41:19.000000000",
    "timeslot": "2 Weeks",
    "insertions": {
        "mean": 5384.357142857143,
        "std": 4763.416398522628,
        "min": 1899.0,
        "25%": 2753.0,
        "50%": 3903.5,
        "75%": 6101.25,
        "max": 20264.0
    },
    "deletions": {
        "mean": 1959.357142857143,
        "std": 1344.2572216737308,
        "min": 571.0,
        "25%": 1078.75,
        "50%": 1397.5,
        "75%": 2663.0,
        "max": 5414.0
    },
    "lines": {
        "mean": 7343.714285714285,
        "std": 5744.2936960025,
        "min": 2552.0,
        "25%": 3831.75,
        "50%": 5139.5,
        "75%": 8965.0,
        "max": 23606.0
    },
    "files": {
        "mean": 323.5,
        "std": 114.43960449478614,
        "min": 135.0,
        "25%": 287.25,
        "50%": 302.5,
        "75%": 369.25,
        "max": 558.0
    },
    "authors": {
        "mean": 1.0,
        "std": 0.0,
        "min": 1.0,
        "25%": 1.0,
        "50%": 1.0,
        "75%": 1.0,
        "max": 1.0
    },
    "addedlines": {
        "mean": 3425.0,
        "std": 3999.6770446547885,
        "min": 862.0,
        "25%": 1753.75,
        "50%": 2232.0,
        "75%": 3178.75,
        "max": 16922.0
    }
}
